src/acumulador.v
`timescale 1ns / 1ps

module acumulador (
    input  wire       clk,
    input  wire       rst,      // Reset síncrono general
    input  wire       start,    // Pulso de inicio (1 ciclo)
    input  wire       cancel,   // Señal de cancelación inmediata
    input  wire [1:0] mode,     // Selector de modo de operación
    input  wire [3:0] x,        // Valor de entrada
    output reg  [5:0] acc,      // Acumulador (6 bits soporta hasta 63)
    output reg        done      // Pulso de 1 ciclo al completar exitosamente
);

    // Codificación de Estados
    localparam IDLE = 2'b00;
    localparam LOAD = 2'b01;
    localparam ADD  = 2'b10;
    localparam DONE = 2'b11;

    reg [1:0] state, next_state;
    reg [2:0] count; // Contador de iteraciones (hasta 7)

    // 1. Registro de Estado (Secuencial sincrónico)
    always @(posedge clk) begin
        if (rst) begin
            state <= IDLE;
        end else begin
            state <= next_state;
        end
    end

    // 2. Lógica Combinacional de Siguiente Estado
    always @(*) begin
        next_state = state;

        case (state)
            IDLE: begin
                if (start && !cancel)
                    next_state = LOAD;
                else
                    next_state = IDLE;
            end

            LOAD: begin
                if (cancel)
                    next_state = IDLE;
                else
                    next_state = ADD;
            end

            ADD: begin
                if (cancel) begin
                    next_state = IDLE; // Aborta inmediatamente
                end else begin
                    case (mode)
                        // Modo 0: Sumar 3 veces (cuenta: 0, 1, 2 -> termina en 2)
                        2'b00: begin
                            if (count == 3'd2)
                                next_state = DONE;
                            else
                                next_state = ADD;
                        end

                        // Modo 1: Sumar 4 veces (cuenta: 0, 1, 2, 3 -> termina en 3)
                        2'b01: begin
                            if (count == 3'd3)
                                next_state = DONE;
                            else
                                next_state = ADD;
                        end

                        // Modo 2: Sumar hasta que acc + x >= 20
                        2'b10: begin
                            if ((acc + x) >= 6'd20)
                                next_state = DONE;
                            else
                                next_state = ADD;
                        end

                        default: next_state = IDLE;
                    endcase
                end
            end

            DONE: begin
                next_state = IDLE; // Permanece 1 ciclo en DONE y retorna
            end

            default: next_state = IDLE;
        endcase
    end

    // 3. Datapath y Salidas (Secuencial sincrónico)
    always @(posedge clk) begin
        if (rst || cancel) begin
            acc   <= 6'd0;
            count <= 3'd0;
            done  <= 1'b0;
        end else begin
            case (state)
                IDLE: begin
                    done  <= 1'b0;
                    count <= 3'd0;
                end

                LOAD: begin
                    acc   <= 6'd0; // Limpia el acumulador para la nueva operación
                    count <= 3'd0;
                    done  <= 1'b0;
                end

                ADD: begin
                    acc   <= acc + x;       // Suma el valor actual de x
                    count <= count + 1'b1;  // Incrementa contador de ciclos
                    done  <= 1'b0;
                end

                DONE: begin
                    done  <= 1'b1; // Señal activa solo durante el estado DONE
                end
            endcase
        end
    end

endmodule

src/tb_acumulador.v
`timescale 1ns / 1ps

module tb_acumulador;

    reg        clk;
    reg        rst;
    reg        start;
    reg        cancel;
    reg  [1:0] mode;
    reg  [3:0] x;
    wire [5:0] acc;
    wire       done;

    // Instancia del módulo bajo prueba (UUT)
    acumulador uut (
        .clk(clk),
        .rst(rst),
        .start(start),
        .cancel(cancel),
        .mode(mode),
        .x(x),
        .acc(acc),
        .done(done)
    );

    // Reloj: Período de 10ns (50 MHz)
    always #5 clk = ~clk;

    initial begin
        $dumpfile("tb_acumulador.vcd");
        $dumpvars(0, tb_acumulador);

        // Inicialización de señales
        clk    = 0;
        rst    = 1;
        start  = 0;
        cancel = 0;
        mode   = 2'b00;
        x      = 4'd0;

        #20;
        rst = 0; // Desactivar reset
        #10;

        // ========================================================
        // PRUEBA 1: Modo 00 -> Sumar x=4, tres (3) veces
        // Resultado esperado: acc = 12
        // ========================================================
        mode  = 2'b00;
        x     = 4'd4;
        start = 1;
        #10;
        start = 0;

        @(posedge done);
        #20;

        // ========================================================
        // PRUEBA 2: Modo 01 -> Sumar x=3, cuatro (4) veces
        // Resultado esperado: acc = 12
        // ========================================================
        mode  = 2'b01;
        x     = 4'd3;
        start = 1;
        #10;
        start = 0;

        @(posedge done);
        #20;

        // ========================================================
        // PRUEBA 3: Modo 10 -> Sumar x=6 hasta que acc >= 20
        // Secuencia: 6, 12, 18, 24 -> Termina con acc = 24
        // ========================================================
        mode  = 2'b10;
        x     = 4'd6;
        start = 1;
        #10;
        start = 0;

        @(posedge done);
        #20;

        // ========================================================
        // PRUEBA 4: Cancelación en pleno proceso
        // Iniciamos con modo 4 sumas, pero enviamos cancel al 2do ciclo
        // ========================================================
        mode  = 2'b01;
        x     = 4'd5;
        start = 1;
        #10;
        start = 0;

        // Esperar a que entre al estado ADD (unos 15 ns) y aplicar cancel
        #15;
        cancel = 1;
        #10;
        cancel = 0;

        #40;
        $display("Pruebas completadas exitosamente.");
        $finish;
    end

endmodule

tb_acumulador.vcd
$date
	Sun Sep 13 18:04:26 2026
$end
$version
	Icarus Verilog
$end
$timescale
	1ps
$end
$scope module tb_acumulador $end
$var wire 1 ! done $end
$var wire 6 " acc [5:0] $end
$var reg 1 # cancel $end
$var reg 1 $ clk $end
$var reg 2 % mode [1:0] $end
$var reg 1 & rst $end
$var reg 1 ' start $end
$var reg 4 ( x [3:0] $end
$scope module uut $end
$var wire 1 # cancel $end
$var wire 1 $ clk $end
$var wire 2 ) mode [1:0] $end
$var wire 1 & rst $end
$var wire 1 ' start $end
$var wire 4 * x [3:0] $end
$var parameter 2 + ADD $end
$var parameter 2 , DONE $end
$var parameter 2 - IDLE $end
$var parameter 2 . LOAD $end
$var reg 6 / acc [5:0] $end
$var reg 3 0 count [2:0] $end
$var reg 1 ! done $end
$var reg 2 1 next_state [1:0] $end
$var reg 2 2 state [1:0] $end
$upscope $end
$upscope $end
$enddefinitions $end
$comment Show the parameter values. $end
$dumpall
b1 .
b0 -
b11 ,
b10 +
$end
#0
$dumpvars
bx 2
b0 1
bx 0
bx /
b0 *
b0 )
b0 (
0'
1&
b0 %
0$
0#
bx "
x!
$end
#5000
b0 2
0!
b0 0
b0 "
b0 /
1$
#10000
0$
#15000
1$
#20000
0$
0&
#25000
1$
#30000
b1 1
0$
1'
b100 (
b100 *
#35000
b10 1
b1 2
1$
#40000
b10 1
0$
0'
#45000
b10 2
1$
#50000
0$
#55000
b1 0
b100 "
b100 /
1$
#60000
0$
#65000
b11 1
b10 0
b1000 "
b1000 /
1$
#70000
0$
#75000
b0 1
b11 0
b1100 "
b1100 /
b11 2
1$
#80000
0$
#85000
b0 2
1!
1$
#90000
0$
#95000
b0 0
0!
1$
#100000
0$
#105000
b1 2
b10 1
1$
1'
b11 (
b11 *
b1 %
b1 )
#110000
0$
#115000
b0 "
b0 /
b10 2
b10 1
1$
0'
#120000
0$
#125000
b1 0
b11 "
b11 /
1$
#130000
0$
#135000
b10 0
b110 "
b110 /
1$
#140000
0$
#145000
b11 1
b11 0
b1001 "
b1001 /
1$
#150000
0$
#155000
b0 1
b100 0
b1100 "
b1100 /
b11 2
1$
#160000
0$
#165000
b0 2
1!
1$
#170000
0$
#175000
b0 0
0!
1$
#180000
0$
#185000
b1 2
b10 1
1$
1'
b110 (
b110 *
b10 %
b10 )
#190000
0$
#195000
b0 "
b0 /
b10 2
b10 1
1$
0'
#200000
0$
#205000
b1 0
b110 "
b110 /
1$
#210000
0$
#215000
b10 0
b1100 "
b1100 /
1$
#220000
0$
#225000
b11 1
b11 0
b10010 "
b10010 /
1$
#230000
0$
#235000
b0 1
b100 0
b11000 "
b11000 /
b11 2
1$
#240000
0$
#245000
b0 2
1!
1$
#250000
0$
#255000
b0 0
0!
1$
#260000
0$
#265000
b1 2
b10 1
1$
1'
b101 (
b101 *
b1 %
b1 )
#270000
0$
#275000
b0 "
b0 /
b10 2
b10 1
1$
0'
#280000
0$
#285000
b1 0
b101 "
b101 /
1$
#290000
b0 1
0$
1#
#295000
b0 0
b0 "
b0 /
b0 2
1$
#300000
0$
0#
