src/semaforo.v
module semaforo (
    input clk,
    input rst,
    output reg green,
    output reg yellow,
    output reg red
);

    // Estados
    parameter S0 = 2'b00;
    parameter S1 = 2'b01;
    parameter S2 = 2'b10;
    parameter S3 = 2'b11;

    // Estado actual
    reg [1:0] state;

    // Contador de ciclos
    reg [2:0] counter;


    // Registro de estado + contador + reset
    always @(posedge clk) begin

        if (rst) begin
            state <= S0;
            counter <= 0;
        end

        else begin

            case (state)

                S0: begin
                    if (counter == 4) begin
                        state <= S1;
                        counter <= 0;
                    end
                    else begin
                        counter <= counter + 1;
                    end
                end

                S1: begin
                    if (counter == 1) begin
                        state <= S2;
                        counter <= 0;
                    end
                    else begin
                        counter <= counter + 1;
                    end
                end

                S2: begin
                    if (counter == 3) begin
                        state <= S3;
                        counter <= 0;
                    end
                    else begin
                        counter <= counter + 1;
                    end
                end

                S3: begin
                    if (counter == 1) begin
                        state <= S0;
                        counter <= 0;
                    end
                    else begin
                        counter <= counter + 1;
                    end
                end

                default: begin
                    state <= S0;
                    counter <= 0;
                end

            endcase

        end

    end


    // Lógica de salidas
    always @(*) begin

        green = 0;
        yellow = 0;
        red = 0;

        case (state)

            S0:
                green = 1;

            S1:
                yellow = 1;

            S2:
                red = 1;

            S3:
                yellow = 1;

        endcase

    end

endmodule

src/tb_semaforo.v
`timescale 1ns/1ps

module tb_semaforo;

    reg clk;
    reg rst;

    wire green;
    wire yellow;
    wire red;
    initial begin

    $dumpfile("semaforo.vcd");
    $dumpvars(0, tb_semaforo);

    clk = 0;
    rst = 1;

    #20;

    rst = 0;

    #150;

    $finish;

end

    // Instancia del semáforo
    semaforo dut (
        .clk(clk),
        .rst(rst),
        .green(green),
        .yellow(yellow),
        .red(red)
    );

    // Generación del reloj
    always #5 clk = ~clk;

    // Prueba
    initial begin

        clk = 0;
        rst = 1;

        // Mantener reset durante algunos ciclos
        #20;

        rst = 0;

        // Dejar correr la FSM
        #150;

        $finish;

    end

    // Mostrar señales en la terminal
    always @(posedge clk) begin
        $strobe("t=%0t | rst=%b | state=%b | counter=%d | G=%b Y=%b R=%b",
                $time, rst, dut.state, dut.counter,
                green, yellow, red);
    end

endmodule

src/semaforo.vcd
$date
	Sat Sep 19 16:03:13 2026
$end
$version
	Icarus Verilog
$end
$timescale
	1ps
$end
$scope module tb_semaforo $end
$var wire 1 ! yellow $end
$var wire 1 " red $end
$var wire 1 # green $end
$var reg 1 $ clk $end
$var reg 1 % rst $end
$scope module dut $end
$var wire 1 $ clk $end
$var wire 1 % rst $end
$var parameter 2 & S0 $end
$var parameter 2 ' S1 $end
$var parameter 2 ( S2 $end
$var parameter 2 ) S3 $end
$var reg 3 * counter [2:0] $end
$var reg 1 # green $end
$var reg 1 " red $end
$var reg 2 + state [1:0] $end
$var reg 1 ! yellow $end
$upscope $end
$upscope $end
$enddefinitions $end
$comment Show the parameter values. $end
$dumpall
b11 )
b10 (
b1 '
b0 &
$end
#0
$dumpvars
bx +
bx *
1%
0$
x#
x"
x!
$end
#5000
0"
0!
1#
b0 *
b0 +
1$
#10000
0$
#15000
1$
#20000
0$
0%
#25000
b1 *
1$
#30000
0$
#35000
b10 *
1$
#40000
0$
#45000
b11 *
1$
#50000
0$
#55000
b100 *
1$
#60000
0$
#65000
1!
0#
b0 *
b1 +
1$
#70000
0$
#75000
b1 *
1$
#80000
0$
#85000
1"
0!
b0 *
b10 +
1$
#90000
0$
#95000
b1 *
1$
#100000
0$
#105000
b10 *
1$
#110000
0$
#115000
b11 *
1$
#120000
0$
#125000
1!
0"
b0 *
b11 +
1$
#130000
0$
#135000
b1 *
1$
#140000
0$
#145000
1#
0!
b0 *
b0 +
1$
#150000
0$
#155000
b1 *
1$
#160000
0$
#165000
b10 *
1$
